{
  "nodeId": "hist_upadek_ocalenie",
  "style": "kids",
  "title": "Bramka Floriańska — historia, która przetrwała",
  "text": "W średniowieczu w największych miastach budowano wysokie mury, żeby chronić je przed atakami. To była taka wielka, mocna osłona! Ale w XVII wieku zaczęły się zmieniać sposoby wojowania. Nowe bronie, jak armaty, sprawiły, że mury już nie były takie skuteczne. Utrzymanie ich było drogie, a niektórzy zaczęli je zaniedbywać. \n\nBrama Floriańska, będąca częścią murów, traciła na znaczeniu. Fosy, które kiedyś były głębokimi rowami z wodą, zaczęto zasypać, a baszty wykorzystywano do przechowywania różnych rzeczy zamiast pełnienia funkcji obronnych. Wszyscy mówili, że te stare mury przeszkadzają w rozwoju miasta. \n\nW latach 1817–1830 złożono nawet plany, żeby zburzyć Bramę Floriańską i wszystkie mury. Ale na szczęście pojawił się Feliks Radwański, który bardzo się zatroszczył o to miejsce. Przekonywał ludzi, że jeśli zburzą bramę, stracą część swojej historii i kultury! \n\nDzięki jego staraniom udało się ocalić Bramę Floriańską. Zaczęto ją odnawiać, żeby była piękna i aby przypominała o dawnych czasach. Dzisiaj brama jest symbolem naszej historii i kultury, a także pamiątką z czasów zaborów, kiedy Polska była podzielona. To ważne miejsce, bo przypomina nam o naszych korzeniach!",
  "generatedAt": "2025-12-27T11:39:13.529Z"
}