{
  "nodeId": "cult_legendy",
  "style": "vulgar",
  "title": "Brama Floriańska — kurwa, co za historia!",
  "text": "Słuchaj, według lokalnych gadek, św. Florian to taki gość, który pilnował tej północnej części miasta i w ogóle bramy przed cholerą pożarami. Jego podobizna wisi na fasadzie jak jakiś zjebany symbol ochrony, żeby strażnicy czuli się bezpieczni. Kurwa, ta legenda niby nie ma nic do roboty z samą budową bramy, ale wszyscy jakoś to ze sobą zeszli i zrobili z tego jeden wielki melanż kulturowy. No i te całe dekoracje, dały bramie wymiar, kurde, symboliczny i narodowy, przekształcając ją z pierdolonego budynku militarnego w ikonę, która teraz ma swoje miejsce w historii i kulturze. Chuj z militariów, teraz mówimy o tradycji!",
  "generatedAt": "2025-12-27T11:39:56.097Z"
}