{
  "nodeId": "arch_materialy",
  "style": "vulgar",
  "title": "Kurwa, mury Bramy Floriańskiej",
  "text": "Dolne partie tej jebanej bramy to kawałek lokalnego wapienia, który jest trwały i da się w miarę ogarnąć przy obróbce. Wyższe kondygnacje to już cholerna cegła, co sprawia, że całość jest lżejsza. I teraz uwaga, grubość murów w przyziemiu to grubo ponad 2 metry, więc nie ma się co dziwić, że stoi jak skała. W środku masz drewniane stropy, które później wrzucili na tapetę podczas restauracji, żeby nie pierdolili się z konstrukcją. Te wszystkie materiały łączą się w jedną, stabilną hybrydę, typową dla obronnych budowli w Krakowie. Jak na takie czasy, to nie ma co marudzić, faktycznie zrobili coś konkretnego.",
  "generatedAt": "2025-12-27T11:39:30.496Z"
}