{
  "nodeId": "root_brama",
  "style": "funny",
  "title": "Brama Floriańska — wprowadzenie na wesoło",
  "text": "Brama Floriańska to najważniejsza zachowana brama miejska Krakowa, będąca częścią średniowiecznego systemu fortyfikacji. (Tak, to ona—i ma się czym pochwalić.) Przez ponad 700 lat pełniła funkcję militarnego wejścia do miasta, punktu kontroli handlu oraz ceremonialnego początku Drogi Królewskiej. Jej architektura, symbolika i historia tworzą wielowarstwową opowieść o obronności, prestiżu i ciągłości miejskiej tradycji.",
  "generatedAt": "2025-12-24T14:08:21.503Z"
}